matter_tool/__init__.py
matter_tool/__main__.py
matter_tool/cli.py
matter_tool/error.py
matter_tool/api/ChipToolMgr.py
matter_tool/api/OTBRMgr.py
matter_tool/api/__init__.py
matter_tool/api/struct/ChipToolData.py
matter_tool/api/struct/OTBRData.py
matter_tool/api/struct/__init__.py
matter_tool/extlib/__init__.py
matter_tool/extlib/CMDAccess/CMDAccess.py
matter_tool/extlib/CMDAccess/__init__.py
matter_tool/extlib/CMDAccess/struct/CMD_data.py
matter_tool/extlib/CMDAccess/struct/ChipToolData.py
matter_tool/extlib/CMDAccess/struct/__init__.py
matter_tool/extlib/TyperExt/TyperExt.py
matter_tool/extlib/TyperExt/__init__.py
matter_tool/module/__init__.py
matter_tool/module/data/Database.py
matter_tool/module/data/MatterDM.py
matter_tool/module/data/__init__.py
rafalmicro_matter_tool-0.0.0.dist-info/METADATA
rafalmicro_matter_tool-0.0.0.dist-info/WHEEL
rafalmicro_matter_tool-0.0.0.dist-info/entry_points.txt
rafalmicro_matter_tool-0.0.0.dist-info/top_level.txt
rafalmicro_matter_tool-0.0.0.dist-info/RECORD
