Metadata-Version: 2.1
Name: rafalmicro-matter-tool
Version: 0.0.0
Summary: Matter controller cli-tool (Support by Rafael Micro)
Home-page: 
Download-URL: https://pypi.org/project/rafalmicro-matter-tool/
Author: resghst
Author-email: hank181017@gmail.com
Classifier: Programming Language :: Python :: 3.7
Classifier: Programming Language :: Python :: 3.8
Classifier: Programming Language :: Python :: 3.9
Classifier: Programming Language :: Python :: 3.10
Classifier: Programming Language :: Python :: 3.11
Requires-Python: >=3.7
Requires-Dist: typer (==0.3.2)
Requires-Dist: colorama (==0.4.4)
Requires-Dist: shellingham (==1.4.0)
Requires-Dist: pytest (==6.2.4)
Requires-Dist: prettytable (==3.7.0)
Requires-Dist: wcwidth (==0.2.6)
